{
  "build": {
    "core": "stm32",
    "cpu": "cortex-m4",
    "extra_flags": "-DSTM32L452xx", 
    "f_cpu": "80000000L",
    "mcu": "stm32l452ret6",
    "product_line": "STM32L452xx",
    "variant": "STM32L4xx/Leafony_STM32"
  },
  "connectivity": [
    "can"
  ],
  "debug": {
    "default_tools": [
      "stlink"
    ],
    "jlink_device": "STM32L452RE",
    "onboard_tools": [
      "stlink"
    ],
    "openocd_board": "st_nucleo_l4",
    "openocd_target": "stm32l4x",
    "svd_path": "STM32L4x2.svd"
  },
  "frameworks": [
    "arduino",
    "cmsis",
    "stm32cube",
    "libopencm3"
  ],
  "name": "Leafony",
  "upload": {
    "maximum_ram_size": 163840,
    "maximum_size": 524288,
    "protocol": "stlink",
    "protocols": [
      "jlink",
      "cmsis-dap",
      "stlink",
      "blackmagic",
      "mbed"
    ]
  },
  "url": "https://shop.leafony.com/",
  "vendor": "Leafony"
}
