{
  "build": {
    "stm32cube": {
      "extra_flags": "-DSTM32L052xx",
      "startup_variant": "stm32l052xx"
    }
  },
  "debug": {
    "jlink_device": "STM32L052T8",
    "openocd_target": "stm32l0x",
    "svd_path": "STM32L052x.svd"
  },
  "device": {
    "communication": {
      "i2c": 2,
      "spi": 1,
      "usart": 2,
      "usb": 1
    },
    "cpu": "cortex-m0plus",
    "f_cpu": "32000000",
    "family": "stm32l0",
    "mcu": "stm32l052t8yx",
    "memory": {
      "flash": 65536,
      "ram": 8192
    },
    "power": {
      "vmax": 3.6,
      "vmin": 1.65
    }
  },
  "frameworks": [
    "stm32cube"
  ],
  "name": "STM32L052T8YX",
  "upload": {
    "maximum_ram_size": 8192,
    "maximum_size": 65536,
    "protocol": "serial",
    "protocols": [
      "jlink",
      "blackmagic",
      "serial",
      "dfu",
      "stlink"
    ]
  },
  "url": "https://www.st.com/content/st_com/en/products/microcontrollers-microprocessors/stm32-32-bit-arm-cortex-mcus/stm32-ultra-low-power-mcus/stm32l0-series/stm32l0x2/stm32l052t8.html",
  "vendor": "STMicroelectronics",
  "version": 2
}
